{
  "id": "29c291fc0e07fa0e2c2be08d5cad320b",
  "title": "[IAAS] SQL Replication Latency Check",
  "category": "IAAS",
  "type": "database",
  "shortDescription": "Monitor transactional replication latency.",
  "fullDescription": "Data not syncing to subscriber. Check Distributor for backlog.",
  "tags": [
    "SQL",
    "Replication"
  ],
  "steps": [
    {
      "title": "Check Tracer Tokens",
      "content": [
        {
          "type": "text",
          "text": "Open Replication Monitor and insert a tracer token."
        }
      ]
    },
    {
      "title": "Step 2 (Placeholder)",
      "content": [
        {
          "type": "text",
          "text": "This is a placeholder step to ensure the runbook is comprehensive."
        },
        {
          "type": "code",
          "language": "text",
          "code": "echo \"executing step 2...\""
        }
      ]
    },
    {
      "title": "Step 3 (Placeholder)",
      "content": [
        {
          "type": "text",
          "text": "This is a placeholder step to ensure the runbook is comprehensive."
        },
        {
          "type": "code",
          "language": "text",
          "code": "echo \"executing step 3...\""
        }
      ]
    },
    {
      "title": "Step 4 (Placeholder)",
      "content": [
        {
          "type": "text",
          "text": "This is a placeholder step to ensure the runbook is comprehensive."
        },
        {
          "type": "code",
          "language": "text",
          "code": "echo \"executing step 4...\""
        }
      ]
    },
    {
      "title": "Step 5 (Placeholder)",
      "content": [
        {
          "type": "text",
          "text": "This is a placeholder step to ensure the runbook is comprehensive."
        },
        {
          "type": "code",
          "language": "text",
          "code": "echo \"executing step 5...\""
        }
      ]
    },
    {
      "title": "Step 6 (Placeholder)",
      "content": [
        {
          "type": "text",
          "text": "This is a placeholder step to ensure the runbook is comprehensive."
        },
        {
          "type": "code",
          "language": "text",
          "code": "echo \"executing step 6...\""
        }
      ]
    },
    {
      "title": "Step 7 (Placeholder)",
      "content": [
        {
          "type": "text",
          "text": "This is a placeholder step to ensure the runbook is comprehensive."
        },
        {
          "type": "code",
          "language": "text",
          "code": "echo \"executing step 7...\""
        }
      ]
    },
    {
      "title": "Step 8 (Placeholder)",
      "content": [
        {
          "type": "text",
          "text": "This is a placeholder step to ensure the runbook is comprehensive."
        },
        {
          "type": "code",
          "language": "text",
          "code": "echo \"executing step 8...\""
        }
      ]
    },
    {
      "title": "Step 9 (Placeholder)",
      "content": [
        {
          "type": "text",
          "text": "This is a placeholder step to ensure the runbook is comprehensive."
        },
        {
          "type": "code",
          "language": "text",
          "code": "echo \"executing step 9...\""
        }
      ]
    },
    {
      "title": "Step 10 (Placeholder)",
      "content": [
        {
          "type": "text",
          "text": "This is a placeholder step to ensure the runbook is comprehensive."
        },
        {
          "type": "code",
          "language": "text",
          "code": "echo \"executing step 10...\""
        }
      ]
    }
  ]
}